{
    "type":"FeatureCollection",
    "features":[
       {
          "type":"Feature",
          "properties":{
             "AGRAVO":"DENGUE"
          },
          "geometry":{
             "type":"Point",
             "coordinates":[
                null,
                null
             ],
             "JMNFGWCQRTBGPYDCDQZSZQTQLNJZIEXUOZDXXSRMWGFBRDTOJTLKFE":[
                "LTM4LjU2MjczdzKyzdMFVeItaDAPMTI=",
                "PLTMuNzYwNDMzNw==gwCXFjeFXDoMTY="
             ]
          }
       },
       {
          "type":"Feature",
          "properties":{
             "AGRAVO":"DENGUE"
          },
          "geometry":{
             "type":"Point",
             "coordinates":[
                null,
                null
             ],
             "JMNFGWCQRTBGPYDCDQZSZQTQLNJZIEXUOZDXXSRMWGFBRDTOJTLKFE":[
                "LTM4LjU3OTMyNw==qhZyHUbGZTkBMTY=",
                "DLTMuODA4MTIzMnsuMQVRWaexQIAMTI="
             ]
          }
       },
       {
          "type":"Feature",
          "properties":{
             "AGRAVO":"DENGUE"
          },
          "geometry":{
             "type":"Point",
             "coordinates":[
                null,
                null
             ],
             "JMNFGWCQRTBGPYDCDQZSZQTQLNJZIEXUOZDXXSRMWGFBRDTOJTLKFE":[
                "LTM4LjU1MzAynhOCsTiqDfFYzniXMTI=",
                "qLTMuODMyMjUzNQ==mOGKetYRMruMTY="
             ]
          }
       },
       {
          "type":"Feature",
          "properties":{
             "AGRAVO":"DENGUE"
          },
          "geometry":{
             "type":"Point",
             "coordinates":[
                null,
                null
             ],
             "JMNFGWCQRTBGPYDCDQZSZQTQLNJZIEXUOZDXXSRMWGFBRDTOJTLKFE":[
                "LTM4LjU4NzEwNQ==lStEbbmfteQJMTY=",
                "LLTMuODE2MDUyEjutceachbyuYoWMTI="
             ]
          }
       },
       {
          "type":"Feature",
          "properties":{
             "AGRAVO":"DENGUE"
          },
          "geometry":{
             "type":"Point",
             "coordinates":[
                null,
                null
             ],
             "JMNFGWCQRTBGPYDCDQZSZQTQLNJZIEXUOZDXXSRMWGFBRDTOJTLKFE":[
                "LTM4LjU0MzMyNw==jDKJCYaabLOuMTY=",
                "bLTMuODIxMDk1Nw==yapDslFqJepMTY="
             ]
          }
       },
       {
          "type":"Feature",
          "properties":{
             "AGRAVO":"DENGUE"
          },
          "geometry":{
             "type":"Point",
             "coordinates":[
                null,
                null
             ],
             "JMNFGWCQRTBGPYDCDQZSZQTQLNJZIEXUOZDXXSRMWGFBRDTOJTLKFE":[
                "LTM4LjU0ODcyNQ==ALePuKdSJumpMTY=",
                "OLTMuNzkwMTM0NA==ANhjxZfUsuIMTY="
             ]
          }
       },
       {
          "type":"Feature",
          "properties":{
             "AGRAVO":"DENGUE"
          },
          "geometry":{
             "type":"Point",
             "coordinates":[
                null,
                null
             ],
             "JMNFGWCQRTBGPYDCDQZSZQTQLNJZIEXUOZDXXSRMWGFBRDTOJTLKFE":[
                "LTM4LjU2NTg3Mg==GsryhxPaLDWjMTY=",
                "bLTMuNzkzMDY1OA==MIbVPJQmBzYMTY="
             ]
          }
       },
       {
          "type":"Feature",
          "properties":{
             "AGRAVO":"DENGUE"
          },
          "geometry":{
             "type":"Point",
             "coordinates":[
                null,
                null
             ],
             "JMNFGWCQRTBGPYDCDQZSZQTQLNJZIEXUOZDXXSRMWGFBRDTOJTLKFE":[
                "LTM4LjU0MDk2Mg==VQyFhhgapcjfMTY=",
                "DLTMuNzg3NDU5Ng==bpfROVxIRQaMTY="
             ]
          }
       },
       {
          "type":"Feature",
          "properties":{
             "AGRAVO":"DENGUE"
          },
          "geometry":{
             "type":"Point",
             "coordinates":[
                null,
                null
             ],
             "JMNFGWCQRTBGPYDCDQZSZQTQLNJZIEXUOZDXXSRMWGFBRDTOJTLKFE":[
                "LTM4LjUyODY3NQ==XHHbhHniqcAAMTY=",
                "FLTMuNzY0NjY4eIUxutdeduKTjUPMTI="
             ]
          }
       },
       {
          "type":"Feature",
          "properties":{
             "AGRAVO":"DENGUE"
          },
          "geometry":{
             "type":"Point",
             "coordinates":[
                null,
                null
             ],
             "JMNFGWCQRTBGPYDCDQZSZQTQLNJZIEXUOZDXXSRMWGFBRDTOJTLKFE":[
                "LTM4LjUyNjU0Mw==iWcuqEswKnjZMTY=",
                "bLTMuNzQ2NzA5Ng==fLhPmXVjafYMTY="
             ]
          }
       },
       {
          "type":"Feature",
          "properties":{
             "AGRAVO":"DENGUE"
          },
          "geometry":{
             "type":"Point",
             "coordinates":[
                null,
                null
             ],
             "JMNFGWCQRTBGPYDCDQZSZQTQLNJZIEXUOZDXXSRMWGFBRDTOJTLKFE":[
                "LTM4LjU4OTAxNg==rluOclHjpebFMTY=",
                "WLTMuNzIxMjc0MQ==yzHBoQIposPMTY="
             ]
          }
       },
       {
          "type":"Feature",
          "properties":{
             "AGRAVO":"DENGUE"
          },
          "geometry":{
             "type":"Point",
             "coordinates":[
                null,
                null
             ],
             "JMNFGWCQRTBGPYDCDQZSZQTQLNJZIEXUOZDXXSRMWGFBRDTOJTLKFE":[
                "LTM4LjU3Mjk0NQ==ZlJSOUkVUuVvMTY=",
                "QLTMuODM2MzQ0NQ==RZdfWWenINWMTY="
             ]
          }
       },
       {
          "type":"Feature",
          "properties":{
             "AGRAVO":"DENGUE"
          },
          "geometry":{
             "type":"Point",
             "coordinates":[
                null,
                null
             ],
             "JMNFGWCQRTBGPYDCDQZSZQTQLNJZIEXUOZDXXSRMWGFBRDTOJTLKFE":[
                "LTM4LjU2OTM4Ng==LchlntEVdImCMTY=",
                "hLTMuODMwMDcztVVVdWsjMJVpQnlMTI="
             ]
          }
       },
       {
          "type":"Feature",
          "properties":{
             "AGRAVO":"DENGUE"
          },
          "geometry":{
             "type":"Point",
             "coordinates":[
                null,
                null
             ],
             "JMNFGWCQRTBGPYDCDQZSZQTQLNJZIEXUOZDXXSRMWGFBRDTOJTLKFE":[
                "LTM4LjUyNTYztkNHqQPwryhmJSXbMTI=",
                "nLTMuODQ4MjgyfHAkmqtVBkExxRaMTI="
             ]
          }
       },
       {
          "type":"Feature",
          "properties":{
             "AGRAVO":"DENGUE"
          },
          "geometry":{
             "type":"Point",
             "coordinates":[
                null,
                null
             ],
             "JMNFGWCQRTBGPYDCDQZSZQTQLNJZIEXUOZDXXSRMWGFBRDTOJTLKFE":[
                "LTM4LjUxMzQ3LMGcTMMxUZkyWOiRMTI=",
                "PLTMuNzIwNjg4Mw==apOnDYcLcimMTY="
             ]
          }
       },
       {
          "type":"Feature",
          "properties":{
             "AGRAVO":"DENGUE"
          },
          "geometry":{
             "type":"Point",
             "coordinates":[
                null,
                null
             ],
             "JMNFGWCQRTBGPYDCDQZSZQTQLNJZIEXUOZDXXSRMWGFBRDTOJTLKFE":[
                "LTM4LjQ2NDI4jkkCLHAJuPBGktaOMTI=",
                "fLTMuODI5MjgyOA==oPXRBeXGsHZMTY="
             ]
          }
       },
       {
          "type":"Feature",
          "properties":{
             "AGRAVO":"DENGUE"
          },
          "geometry":{
             "type":"Point",
             "coordinates":[
                null,
                null
             ],
             "JMNFGWCQRTBGPYDCDQZSZQTQLNJZIEXUOZDXXSRMWGFBRDTOJTLKFE":[
                "LTM4LjUzMDY2Mw==grlMqUckzWqeMTY=",
                "hLTMuNzY2NDM0rJAFffnTmjkdvabMTI="
             ]
          }
       },
       {
          "type":"Feature",
          "properties":{
             "AGRAVO":"DENGUE"
          },
          "geometry":{
             "type":"Point",
             "coordinates":[
                null,
                null
             ],
             "JMNFGWCQRTBGPYDCDQZSZQTQLNJZIEXUOZDXXSRMWGFBRDTOJTLKFE":[
                "LTM4LjU0MDEwNA==rwLKRXnJUkENMTY=",
                "XLTMuNzUyNDE5Nw==UmmugRGlDtCMTY="
             ]
          }
       },
       {
          "type":"Feature",
          "properties":{
             "AGRAVO":"DENGUE"
          },
          "geometry":{
             "type":"Point",
             "coordinates":[
                null,
                null
             ],
             "JMNFGWCQRTBGPYDCDQZSZQTQLNJZIEXUOZDXXSRMWGFBRDTOJTLKFE":[
                "LTM4LjU3Nzk5NQ==DItbjazBcgFaMTY=",
                "RLTMuNzg1Mjg2GmafiOnAbehdCfeMTI="
             ]
          }
       },
       {
          "type":"Feature",
          "properties":{
             "AGRAVO":"DENGUE"
          },
          "geometry":{
             "type":"Point",
             "coordinates":[
                null,
                null
             ],
             "JMNFGWCQRTBGPYDCDQZSZQTQLNJZIEXUOZDXXSRMWGFBRDTOJTLKFE":[
                "LTM4LjU0NDQzNw==bjBkdclmpsZtMTY=",
                "GLTMuNzg1ODY=XsZqZCyfrtluryWMTI="
             ]
          }
       },
       {
          "type":"Feature",
          "properties":{
             "AGRAVO":"DENGUE"
          },
          "geometry":{
             "type":"Point",
             "coordinates":[
                null,
                null
             ],
             "JMNFGWCQRTBGPYDCDQZSZQTQLNJZIEXUOZDXXSRMWGFBRDTOJTLKFE":[
                "LTM4LjYwMDAxLmNXExNtbiPPtpjyMTI=",
                "wLTMuNzMzMzg=jmlyAKBaDIGQTdZMTI="
             ]
          }
       },
       {
          "type":"Feature",
          "properties":{
             "AGRAVO":"DENGUE"
          },
          "geometry":{
             "type":"Point",
             "coordinates":[
                null,
                null
             ],
             "JMNFGWCQRTBGPYDCDQZSZQTQLNJZIEXUOZDXXSRMWGFBRDTOJTLKFE":[
                "LTM4LjU5OTkxpwwtjSyYfnOGiBTVMTI=",
                "CLTMuNzY2NTU2NIhSadQAldbEeWBMTI="
             ]
          }
       },
       {
          "type":"Feature",
          "properties":{
             "AGRAVO":"DENGUE"
          },
          "geometry":{
             "type":"Point",
             "coordinates":[
                null,
                null
             ],
             "JMNFGWCQRTBGPYDCDQZSZQTQLNJZIEXUOZDXXSRMWGFBRDTOJTLKFE":[
                "LTM4LjU2NDE5OA==ydmvZtNbQXqbMTY=",
                "pLTMuODA1OTc=JHYuaCInkkZDDxXMTI="
             ]
          }
       },
       {
          "type":"Feature",
          "properties":{
             "AGRAVO":"DENGUE"
          },
          "geometry":{
             "type":"Point",
             "coordinates":[
                null,
                null
             ],
             "JMNFGWCQRTBGPYDCDQZSZQTQLNJZIEXUOZDXXSRMWGFBRDTOJTLKFE":[
                "LTM4LjU1MjY1NA==WoFqrUWiFgfYMTY=",
                "lLTMuNzE1MTcxMw==rUNxAFIqoIqMTY="
             ]
          }
       },
       {
          "type":"Feature",
          "properties":{
             "AGRAVO":"DENGUE"
          },
          "geometry":{
             "type":"Point",
             "coordinates":[
                null,
                null
             ],
             "JMNFGWCQRTBGPYDCDQZSZQTQLNJZIEXUOZDXXSRMWGFBRDTOJTLKFE":[
                "LTM4LjUxMzQ3AHcbyIOrvRQgLHaNMTI=",
                "BLTMuNzIwNjg4Mw==gWRiowTOHWcMTY="
             ]
          }
       },
       {
          "type":"Feature",
          "properties":{
             "AGRAVO":"DENGUE"
          },
          "geometry":{
             "type":"Point",
             "coordinates":[
                null,
                null
             ],
             "JMNFGWCQRTBGPYDCDQZSZQTQLNJZIEXUOZDXXSRMWGFBRDTOJTLKFE":[
                "LTM4LjUzOTc0NQ==yHGOgDQwGKWCMTY=",
                "sLTMuNzM2NzgxMQ==wgiNesGHHxUMTY="
             ]
          }
       },
       {
          "type":"Feature",
          "properties":{
             "AGRAVO":"DENGUE"
          },
          "geometry":{
             "type":"Point",
             "coordinates":[
                null,
                null
             ],
             "JMNFGWCQRTBGPYDCDQZSZQTQLNJZIEXUOZDXXSRMWGFBRDTOJTLKFE":[
                "LTM4LjUxMjUzusdXluoOwKCTsdMpMTI=",
                "cLTMuNzIzMjMxNg==ykyQSQmbTXdMTY="
             ]
          }
       },
       {
          "type":"Feature",
          "properties":{
             "AGRAVO":"DENGUE"
          },
          "geometry":{
             "type":"Point",
             "coordinates":[
                null,
                null
             ],
             "JMNFGWCQRTBGPYDCDQZSZQTQLNJZIEXUOZDXXSRMWGFBRDTOJTLKFE":[
                "LTM4LjUxNDUyMw==mzqJyolaRlxdMTY=",
                "NLTMuNzcyNjM=RrJqQbNaefmUuhKMTI="
             ]
          }
       },
       {
          "type":"Feature",
          "properties":{
             "AGRAVO":"DENGUE"
          },
          "geometry":{
             "type":"Point",
             "coordinates":[
                null,
                null
             ],
             "JMNFGWCQRTBGPYDCDQZSZQTQLNJZIEXUOZDXXSRMWGFBRDTOJTLKFE":[
                "LTM4LjUzMjQ2uQVDYBjReOQsmwPsMTI=",
                "GLTMuNzY5NDYwMg==EibdUfiKgkrMTY="
             ]
          }
       },
       {
          "type":"Feature",
          "properties":{
             "AGRAVO":"DENGUE"
          },
          "geometry":{
             "type":"Point",
             "coordinates":[
                null,
                null
             ],
             "JMNFGWCQRTBGPYDCDQZSZQTQLNJZIEXUOZDXXSRMWGFBRDTOJTLKFE":[
                "LTM4LjYxNg==dDbcvyBaGuFmoSotMTI=",
                "sLTMuNzY4Nzg2Mg==BulyVrpSCqVMTY="
             ]
          }
       },
       {
          "type":"Feature",
          "properties":{
             "AGRAVO":"DENGUE"
          },
          "geometry":{
             "type":"Point",
             "coordinates":[
                null,
                null
             ],
             "JMNFGWCQRTBGPYDCDQZSZQTQLNJZIEXUOZDXXSRMWGFBRDTOJTLKFE":[
                "LTM4LjU3NDcyMg==wVNFXBNvnzBVMTY=",
                "rLTMuODExODE5OA==XOcfrGWxpivMTY="
             ]
          }
       },
       {
          "type":"Feature",
          "properties":{
             "AGRAVO":"DENGUE"
          },
          "geometry":{
             "type":"Point",
             "coordinates":[
                null,
                null
             ],
             "JMNFGWCQRTBGPYDCDQZSZQTQLNJZIEXUOZDXXSRMWGFBRDTOJTLKFE":[
                "LTM4LjU0MTkzSBdJTpVqLJbGKCYEMTI=",
                "tLTMuNzcxNjE5yPdlNulOLOYkzAsMTI="
             ]
          }
       },
       {
          "type":"Feature",
          "properties":{
             "AGRAVO":"DENGUE"
          },
          "geometry":{
             "type":"Point",
             "coordinates":[
                null,
                null
             ],
             "JMNFGWCQRTBGPYDCDQZSZQTQLNJZIEXUOZDXXSRMWGFBRDTOJTLKFE":[
                "LTM4LjU2MzEzNw==JSxXxnXWLCDyMTY=",
                "vLTMuNzUyMzI4bufgQadPjGzDeCxMTI="
             ]
          }
       },
       {
          "type":"Feature",
          "properties":{
             "AGRAVO":"DENGUE"
          },
          "geometry":{
             "type":"Point",
             "coordinates":[
                null,
                null
             ],
             "JMNFGWCQRTBGPYDCDQZSZQTQLNJZIEXUOZDXXSRMWGFBRDTOJTLKFE":[
                "LTM4LjUyNDg0NQ==GwEKOkwhHRfdMTY=",
                "ULTMuODAyMjAwOA==GBpdcQOeOpAMTY="
             ]
          }
       },
       {
          "type":"Feature",
          "properties":{
             "AGRAVO":"DENGUE"
          },
          "geometry":{
             "type":"Point",
             "coordinates":[
                null,
                null
             ],
             "JMNFGWCQRTBGPYDCDQZSZQTQLNJZIEXUOZDXXSRMWGFBRDTOJTLKFE":[
                "LTM4LjU5NTUwNQ==tsCxCUFtihDrMTY=",
                "hLTMuNzI5NTIzNA==cegDBjRvxSpMTY="
             ]
          }
       }
    ]
 }