{
  "type":"FeatureCollection",
  "features":[
    {
      "type":"Feature",
      "properties":{
        "AGRAVO":"DENGUE"
      },
      "geometry":{
        "type":"Point",
        "coordinates":[
          null,
          null
        ],
        "YZEPBZDRJSEWSDOEWSUWBYEIRJVINSTYQIXVWGRNFIDUJGAYNSIRXXHIZUTRECKPZOC":[
          "LTM4LjYxNzc3NQ==JYkUZYvHOygnMTY=",
          "WLTMuODE3MjU0zxrQRwvrHAzGcfNMTI="
        ]
      }
    },
    {
      "type":"Feature",
      "properties":{
        "AGRAVO":"DENGUE"
      },
      "geometry":{
        "type":"Point",
        "coordinates":[
          null,
          null
        ],
        "YZEPBZDRJSEWSDOEWSUWBYEIRJVINSTYQIXVWGRNFIDUJGAYNSIRXXHIZUTRECKPZOC":[
          "LTM4LjUxMDk3NQ==CgwjeyfugrsWMTY=",
          "fLTMuNzYyMDc3vbSierBFdlHmewcMTI="
        ]
      }
    },
    {
      "type":"Feature",
      "properties":{
        "AGRAVO":"DENGUE"
      },
      "geometry":{
        "type":"Point",
        "coordinates":[
          null,
          null
        ],
        "YZEPBZDRJSEWSDOEWSUWBYEIRJVINSTYQIXVWGRNFIDUJGAYNSIRXXHIZUTRECKPZOC":[
          "LTM4LjUwNTUzzskEYzZjSAOKZyaqMTI=",
          "OLTMuODQ1MDk0Mg==FVtAUoXHoEEMTY="
        ]
      }
    },
    {
      "type":"Feature",
      "properties":{
        "AGRAVO":"DENGUE"
      },
      "geometry":{
        "type":"Point",
        "coordinates":[
          null,
          null
        ],
        "YZEPBZDRJSEWSDOEWSUWBYEIRJVINSTYQIXVWGRNFIDUJGAYNSIRXXHIZUTRECKPZOC":[
          "LTM4LjU3OTA1Mg==ZecWnrbdIxtUMTY=",
          "iLTMuNzA0MTAzNQ==eOeFZFGcBuvMTY="
        ]
      }
    },
    {
      "type":"Feature",
      "properties":{
        "AGRAVO":"DENGUE"
      },
      "geometry":{
        "type":"Point",
        "coordinates":[
          null,
          null
        ],
        "YZEPBZDRJSEWSDOEWSUWBYEIRJVINSTYQIXVWGRNFIDUJGAYNSIRXXHIZUTRECKPZOC":[
          "LTM4LjU3MDA5LdICNFoXSXDasiBRMTI=",
          "yLTMuNzA1MTU5NA==WVEPeNiExOdMTY="
        ]
      }
    },
    {
      "type":"Feature",
      "properties":{
        "AGRAVO":"DENGUE"
      },
      "geometry":{
        "type":"Point",
        "coordinates":[
          null,
          null
        ],
        "YZEPBZDRJSEWSDOEWSUWBYEIRJVINSTYQIXVWGRNFIDUJGAYNSIRXXHIZUTRECKPZOC":[
          "LTM4LjU3NTIxNA==AVPOeoLdMgqRMTY=",
          "ALTMuNzAxNTIzMw==lWsUrLMZyJQMTY="
        ]
      }
    },
    {
      "type":"Feature",
      "properties":{
        "AGRAVO":"DENGUE"
      },
      "geometry":{
        "type":"Point",
        "coordinates":[
          null,
          null
        ],
        "YZEPBZDRJSEWSDOEWSUWBYEIRJVINSTYQIXVWGRNFIDUJGAYNSIRXXHIZUTRECKPZOC":[
          "LTM4LjU4NDY2Mw==xHOrcsJpEayMMTY=",
          "dLTMuNzc1NjM1tzMkfMHJYfPAttXMTI="
        ]
      }
    },
    {
      "type":"Feature",
      "properties":{
        "AGRAVO":"DENGUE"
      },
      "geometry":{
        "type":"Point",
        "coordinates":[
          null,
          null
        ],
        "YZEPBZDRJSEWSDOEWSUWBYEIRJVINSTYQIXVWGRNFIDUJGAYNSIRXXHIZUTRECKPZOC":[
          "LTM4LjYxMDYzOA==DQPgKJvCqIPtMTY=",
          "fLTMuNzcxNzkzAwvgfxwsyjvewBBMTI="
        ]
      }
    },
    {
      "type":"Feature",
      "properties":{
        "AGRAVO":"DENGUE"
      },
      "geometry":{
        "type":"Point",
        "coordinates":[
          null,
          null
        ],
        "YZEPBZDRJSEWSDOEWSUWBYEIRJVINSTYQIXVWGRNFIDUJGAYNSIRXXHIZUTRECKPZOC":[
          "LTM4LjUwMzk4Ng==QwMSaynloSXOMTY=",
          "SLTMuNzg1ODc5NA==RJpVOvoITqBMTY="
        ]
      }
    },
    {
      "type":"Feature",
      "properties":{
        "AGRAVO":"DENGUE"
      },
      "geometry":{
        "type":"Point",
        "coordinates":[
          null,
          null
        ],
        "YZEPBZDRJSEWSDOEWSUWBYEIRJVINSTYQIXVWGRNFIDUJGAYNSIRXXHIZUTRECKPZOC":[
          "LTM4LjU1OTI5SExPTfvMyBERDFjOMTI=",
          "jLTMuODI2Mjc0bppFytwMNDkjroVMTI="
        ]
      }
    },
    {
      "type":"Feature",
      "properties":{
        "AGRAVO":"DENGUE"
      },
      "geometry":{
        "type":"Point",
        "coordinates":[
          null,
          null
        ],
        "YZEPBZDRJSEWSDOEWSUWBYEIRJVINSTYQIXVWGRNFIDUJGAYNSIRXXHIZUTRECKPZOC":[
          "LTM4LjU5MzY5Mw==DaFgIALRtMoVMTY=",
          "KLTMuNzQ4Nzk3Nw==tJqneroxGmwMTY="
        ]
      }
    },
    {
      "type":"Feature",
      "properties":{
        "AGRAVO":"DENGUE"
      },
      "geometry":{
        "type":"Point",
        "coordinates":[
          null,
          null
        ],
        "YZEPBZDRJSEWSDOEWSUWBYEIRJVINSTYQIXVWGRNFIDUJGAYNSIRXXHIZUTRECKPZOC":[
          "LTM4LjQ3ODQypskAhoeVlfQRAYOHMTI=",
          "fLTMuODIzMjk0Ng==JvKSKQpSmfmMTY="
        ]
      }
    },
    {
      "type":"Feature",
      "properties":{
        "AGRAVO":"DENGUE"
      },
      "geometry":{
        "type":"Point",
        "coordinates":[
          null,
          null
        ],
        "YZEPBZDRJSEWSDOEWSUWBYEIRJVINSTYQIXVWGRNFIDUJGAYNSIRXXHIZUTRECKPZOC":[
          "LTM4LjUyOTYzCKReXoKmurmWRRkgMTI=",
          "ZLTMuODIyMDIzHRWZAxMUBvTojhGMTI="
        ]
      }
    },
    {
      "type":"Feature",
      "properties":{
        "AGRAVO":"DENGUE"
      },
      "geometry":{
        "type":"Point",
        "coordinates":[
          null,
          null
        ],
        "YZEPBZDRJSEWSDOEWSUWBYEIRJVINSTYQIXVWGRNFIDUJGAYNSIRXXHIZUTRECKPZOC":[
          "LTM4LjYwMDMyNw==pqZXoaXEJCjTMTY=",
          "JLTMuNzYwMjIyfLEdIVVkKtbRALRMTI="
        ]
      }
    },
    {
      "type":"Feature",
      "properties":{
        "AGRAVO":"DENGUE"
      },
      "geometry":{
        "type":"Point",
        "coordinates":[
          null,
          null
        ],
        "YZEPBZDRJSEWSDOEWSUWBYEIRJVINSTYQIXVWGRNFIDUJGAYNSIRXXHIZUTRECKPZOC":[
          "LTM4LjQ5NDY4Ng==kvIsclvFXsIGMTY=",
          "WLTMuODU5ODg0Mw==WgPjNfwLyVBMTY="
        ]
      }
    },
    {
      "type":"Feature",
      "properties":{
        "AGRAVO":"DENGUE"
      },
      "geometry":{
        "type":"Point",
        "coordinates":[
          null,
          null
        ],
        "YZEPBZDRJSEWSDOEWSUWBYEIRJVINSTYQIXVWGRNFIDUJGAYNSIRXXHIZUTRECKPZOC":[
          "LTM4LjYxMzcxMg==BEGNOVkmTJrgMTY=",
          "eLTMuNzYzNTA4BmbiOaWjwRAfiLKMTI="
        ]
      }
    },
    {
      "type":"Feature",
      "properties":{
        "AGRAVO":"DENGUE"
      },
      "geometry":{
        "type":"Point",
        "coordinates":[
          null,
          null
        ],
        "YZEPBZDRJSEWSDOEWSUWBYEIRJVINSTYQIXVWGRNFIDUJGAYNSIRXXHIZUTRECKPZOC":[
          "LTM4LjUxMzk0Mw==ujKhkZBvsTdNMTY=",
          "YLTMuNzc1MjMzhVZKLGPUqxImCVWMTI="
        ]
      }
    },
    {
      "type":"Feature",
      "properties":{
        "AGRAVO":"DENGUE"
      },
      "geometry":{
        "type":"Point",
        "coordinates":[
          null,
          null
        ],
        "YZEPBZDRJSEWSDOEWSUWBYEIRJVINSTYQIXVWGRNFIDUJGAYNSIRXXHIZUTRECKPZOC":[
          "LTM4LjU3NTk4wRATodtcrJFSuZijMTI=",
          "ZLTMuNzY1ODMzNg==rExAuclwbIBMTY="
        ]
      }
    },
    {
      "type":"Feature",
      "properties":{
        "AGRAVO":"DENGUE"
      },
      "geometry":{
        "type":"Point",
        "coordinates":[
          null,
          null
        ],
        "YZEPBZDRJSEWSDOEWSUWBYEIRJVINSTYQIXVWGRNFIDUJGAYNSIRXXHIZUTRECKPZOC":[
          "LTM4LjU0MDMzPzpLAKxcFrMymNLRMTI=",
          "aLTMuNzYwMjkxhUZFcDtPPQNNEEOMTI="
        ]
      }
    },
    {
      "type":"Feature",
      "properties":{
        "AGRAVO":"DENGUE"
      },
      "geometry":{
        "type":"Point",
        "coordinates":[
          null,
          null
        ],
        "YZEPBZDRJSEWSDOEWSUWBYEIRJVINSTYQIXVWGRNFIDUJGAYNSIRXXHIZUTRECKPZOC":[
          "LTM4LjUyODQ5Mg==RWfkzuvkfWZvMTY=",
          "pLTMuNzMzMjA5NA==GpgXScDmFCBMTY="
        ]
      }
    },
    {
      "type":"Feature",
      "properties":{
        "AGRAVO":"DENGUE"
      },
      "geometry":{
        "type":"Point",
        "coordinates":[
          null,
          null
        ],
        "YZEPBZDRJSEWSDOEWSUWBYEIRJVINSTYQIXVWGRNFIDUJGAYNSIRXXHIZUTRECKPZOC":[
          "LTM4LjU2OTgxMw==vCCumABqWkiDMTY=",
          "CLTMuNzA2NDQ2WDjvkXkHhVjvqmcMTI="
        ]
      }
    },
    {
      "type":"Feature",
      "properties":{
        "AGRAVO":"DENGUE"
      },
      "geometry":{
        "type":"Point",
        "coordinates":[
          null,
          null
        ],
        "YZEPBZDRJSEWSDOEWSUWBYEIRJVINSTYQIXVWGRNFIDUJGAYNSIRXXHIZUTRECKPZOC":[
          "LTM4LjU4MTQ1NQ==VioJsmyiEyEzMTY=",
          "gLTMuNjk4MjQ1NQ==zoKOOVSDFEIMTY="
        ]
      }
    },
    {
      "type":"Feature",
      "properties":{
        "AGRAVO":"DENGUE"
      },
      "geometry":{
        "type":"Point",
        "coordinates":[
          null,
          null
        ],
        "YZEPBZDRJSEWSDOEWSUWBYEIRJVINSTYQIXVWGRNFIDUJGAYNSIRXXHIZUTRECKPZOC":[
          "LTM4LjU2OTAyNw==JSSKqzGuxNTNMTY=",
          "YLTMuNzA2MjkzwPIYLVPXbpbVIRcMTI="
        ]
      }
    },
    {
      "type":"Feature",
      "properties":{
        "AGRAVO":"DENGUE"
      },
      "geometry":{
        "type":"Point",
        "coordinates":[
          null,
          null
        ],
        "YZEPBZDRJSEWSDOEWSUWBYEIRJVINSTYQIXVWGRNFIDUJGAYNSIRXXHIZUTRECKPZOC":[
          "LTM4LjQ2NzYzNg==fyLthFIrwENPMTY=",
          "JLTMuNzg5OTk1uJgIQGkyyFOTxCgMTI="
        ]
      }
    },
    {
      "type":"Feature",
      "properties":{
        "AGRAVO":"DENGUE"
      },
      "geometry":{
        "type":"Point",
        "coordinates":[
          null,
          null
        ],
        "YZEPBZDRJSEWSDOEWSUWBYEIRJVINSTYQIXVWGRNFIDUJGAYNSIRXXHIZUTRECKPZOC":[
          "LTM4LjQ3MDAxNg==KTJbeiIzPFTzMTY=",
          "gLTMuNzkxNTI4Nw==FbpekivGyKcMTY="
        ]
      }
    },
    {
      "type":"Feature",
      "properties":{
        "AGRAVO":"DENGUE"
      },
      "geometry":{
        "type":"Point",
        "coordinates":[
          null,
          null
        ],
        "YZEPBZDRJSEWSDOEWSUWBYEIRJVINSTYQIXVWGRNFIDUJGAYNSIRXXHIZUTRECKPZOC":[
          "LTM4LjUwOTk1ggFxhZzjMLZvuQWXMTI=",
          "bLTMuODYzMzA5IIjVWcNZRrNJXukMTI="
        ]
      }
    },
    {
      "type":"Feature",
      "properties":{
        "AGRAVO":"DENGUE"
      },
      "geometry":{
        "type":"Point",
        "coordinates":[
          null,
          null
        ],
        "YZEPBZDRJSEWSDOEWSUWBYEIRJVINSTYQIXVWGRNFIDUJGAYNSIRXXHIZUTRECKPZOC":[
          "LTM4LjU5MDMxQDKezifatsuQTqfwMTI=",
          "wLTMuODAzMTI3NQ==keSxrjKBJcCMTY="
        ]
      }
    },
    {
      "type":"Feature",
      "properties":{
        "AGRAVO":"DENGUE"
      },
      "geometry":{
        "type":"Point",
        "coordinates":[
          null,
          null
        ],
        "YZEPBZDRJSEWSDOEWSUWBYEIRJVINSTYQIXVWGRNFIDUJGAYNSIRXXHIZUTRECKPZOC":[
          "LTM4LjUxNDQyMw==KVOhKYkEbTeEMTY=",
          "sLTMuNzYxMDQ3MQ==dbzseWVBaIrMTY="
        ]
      }
    },
    {
      "type":"Feature",
      "properties":{
        "AGRAVO":"DENGUE"
      },
      "geometry":{
        "type":"Point",
        "coordinates":[
          null,
          null
        ],
        "YZEPBZDRJSEWSDOEWSUWBYEIRJVINSTYQIXVWGRNFIDUJGAYNSIRXXHIZUTRECKPZOC":[
          "LTM4LjU3NTE1ITTofRGxZSOgwnjUMTI=",
          "xLTMuNzE0Mzg4NA==kABcblCCXtmMTY="
        ]
      }
    },
    {
      "type":"Feature",
      "properties":{
        "AGRAVO":"DENGUE"
      },
      "geometry":{
        "type":"Point",
        "coordinates":[
          null,
          null
        ],
        "YZEPBZDRJSEWSDOEWSUWBYEIRJVINSTYQIXVWGRNFIDUJGAYNSIRXXHIZUTRECKPZOC":[
          "LTM4LjU0MzIwNQ==VvkGlmbxHjHcMTY=",
          "TLTMuNzU3OTM=VRwIyidTuaxtJyQMTI="
        ]
      }
    },
    {
      "type":"Feature",
      "properties":{
        "AGRAVO":"DENGUE"
      },
      "geometry":{
        "type":"Point",
        "coordinates":[
          null,
          null
        ],
        "YZEPBZDRJSEWSDOEWSUWBYEIRJVINSTYQIXVWGRNFIDUJGAYNSIRXXHIZUTRECKPZOC":[
          "LTM4LjU2MzI4Ng==EHENgyZaAhUkMTY=",
          "yLTMuODQwNzkxlLeMTTqIWeVZlWFMTI="
        ]
      }
    },
    {
      "type":"Feature",
      "properties":{
        "AGRAVO":"DENGUE"
      },
      "geometry":{
        "type":"Point",
        "coordinates":[
          null,
          null
        ],
        "YZEPBZDRJSEWSDOEWSUWBYEIRJVINSTYQIXVWGRNFIDUJGAYNSIRXXHIZUTRECKPZOC":[
          "LTM4LjUxNTI4srQJlBNNSuYpVyPuMTI=",
          "ILTMuNzYwODc3NA==FsgEFGtQbxtMTY="
        ]
      }
    },
    {
      "type":"Feature",
      "properties":{
        "AGRAVO":"DENGUE"
      },
      "geometry":{
        "type":"Point",
        "coordinates":[
          null,
          null
        ],
        "YZEPBZDRJSEWSDOEWSUWBYEIRJVINSTYQIXVWGRNFIDUJGAYNSIRXXHIZUTRECKPZOC":[
          "LTM4LjU4NDc0Mw==lPtkcexHlsVmMTY=",
          "CLTMuNzk1OTkyNg==NABHwPEBwIsMTY="
        ]
      }
    },
    {
      "type":"Feature",
      "properties":{
        "AGRAVO":"DENGUE"
      },
      "geometry":{
        "type":"Point",
        "coordinates":[
          null,
          null
        ],
        "YZEPBZDRJSEWSDOEWSUWBYEIRJVINSTYQIXVWGRNFIDUJGAYNSIRXXHIZUTRECKPZOC":[
          "LTM4LjU4MzUyMw==ahXkOUMIXnblMTY=",
          "lLTMuNzg1MDUyNQ==PrpPtMKDiNqMTY="
        ]
      }
    },
    {
      "type":"Feature",
      "properties":{
        "AGRAVO":"DENGUE"
      },
      "geometry":{
        "type":"Point",
        "coordinates":[
          null,
          null
        ],
        "YZEPBZDRJSEWSDOEWSUWBYEIRJVINSTYQIXVWGRNFIDUJGAYNSIRXXHIZUTRECKPZOC":[
          "LTM4LjU3MjM0Mg==FGAecbAMtodoMTY=",
          "BLTMuNzA2MzQ5Ng==fCYMoLJlYAXMTY="
        ]
      }
    },
    {
      "type":"Feature",
      "properties":{
        "AGRAVO":"DENGUE"
      },
      "geometry":{
        "type":"Point",
        "coordinates":[
          null,
          null
        ],
        "YZEPBZDRJSEWSDOEWSUWBYEIRJVINSTYQIXVWGRNFIDUJGAYNSIRXXHIZUTRECKPZOC":[
          "LTM4LjU0MDIyMg==NQvYpfVOqFtSMTY=",
          "YLTMuNzMwMDg0NA==noRbEsDxRHAMTY="
        ]
      }
    },
    {
      "type":"Feature",
      "properties":{
        "AGRAVO":"DENGUE"
      },
      "geometry":{
        "type":"Point",
        "coordinates":[
          null,
          null
        ],
        "YZEPBZDRJSEWSDOEWSUWBYEIRJVINSTYQIXVWGRNFIDUJGAYNSIRXXHIZUTRECKPZOC":[
          "LTM4LjU5MjE2RiuKKFhPgTfkTMPeMTI=",
          "DLTMuNzgxMDc1Nw==VBwBNuNKzJwMTY="
        ]
      }
    },
    {
      "type":"Feature",
      "properties":{
        "AGRAVO":"DENGUE"
      },
      "geometry":{
        "type":"Point",
        "coordinates":[
          null,
          null
        ],
        "YZEPBZDRJSEWSDOEWSUWBYEIRJVINSTYQIXVWGRNFIDUJGAYNSIRXXHIZUTRECKPZOC":[
          "LTM4LjUyNzQwNQ==yGHzmBOZFxVrMTY=",
          "MLTMuODE1NTU4NA==rUOQeykeQpxMTY="
        ]
      }
    },
    {
      "type":"Feature",
      "properties":{
        "AGRAVO":"DENGUE"
      },
      "geometry":{
        "type":"Point",
        "coordinates":[
          null,
          null
        ],
        "YZEPBZDRJSEWSDOEWSUWBYEIRJVINSTYQIXVWGRNFIDUJGAYNSIRXXHIZUTRECKPZOC":[
          "LTM4LjYwNzY=rtarzVevCkqlsczOMTI=",
          "oLTMuNzYzNTg4Nw==VYAYPSexOboMTY="
        ]
      }
    },
    {
      "type":"Feature",
      "properties":{
        "AGRAVO":"DENGUE"
      },
      "geometry":{
        "type":"Point",
        "coordinates":[
          null,
          null
        ],
        "YZEPBZDRJSEWSDOEWSUWBYEIRJVINSTYQIXVWGRNFIDUJGAYNSIRXXHIZUTRECKPZOC":[
          "LTM4LjYwNzE4RkwUqlLOoKVGiAZEMTI=",
          "LLTMuNzg0NzMxLsboyXXPUGVOAbQMTI="
        ]
      }
    },
    {
      "type":"Feature",
      "properties":{
        "AGRAVO":"DENGUE"
      },
      "geometry":{
        "type":"Point",
        "coordinates":[
          null,
          null
        ],
        "YZEPBZDRJSEWSDOEWSUWBYEIRJVINSTYQIXVWGRNFIDUJGAYNSIRXXHIZUTRECKPZOC":[
          "LTM4LjU4OTU5FuEBjbgaTNLEoQjrMTI=",
          "xLTMuNzY5MDcyQuAprBjuqIlrRmbMTI="
        ]
      }
    },
    {
      "type":"Feature",
      "properties":{
        "AGRAVO":"DENGUE"
      },
      "geometry":{
        "type":"Point",
        "coordinates":[
          null,
          null
        ],
        "YZEPBZDRJSEWSDOEWSUWBYEIRJVINSTYQIXVWGRNFIDUJGAYNSIRXXHIZUTRECKPZOC":[
          "LTM4LjU2ODY5NQ==FvdmiMOTLyfqMTY=",
          "cLTMuNzYwMDM0TvndRvtpjnCdZpKMTI="
        ]
      }
    },
    {
      "type":"Feature",
      "properties":{
        "AGRAVO":"DENGUE"
      },
      "geometry":{
        "type":"Point",
        "coordinates":[
          null,
          null
        ],
        "YZEPBZDRJSEWSDOEWSUWBYEIRJVINSTYQIXVWGRNFIDUJGAYNSIRXXHIZUTRECKPZOC":[
          "LTM4LjU1NTc=JhjWTKTbhhkEXacUMTI=",
          "nLTMuNzA5ODU=qqChBMAJShCMKGMMTI="
        ]
      }
    },
    {
      "type":"Feature",
      "properties":{
        "AGRAVO":"DENGUE"
      },
      "geometry":{
        "type":"Point",
        "coordinates":[
          null,
          null
        ],
        "YZEPBZDRJSEWSDOEWSUWBYEIRJVINSTYQIXVWGRNFIDUJGAYNSIRXXHIZUTRECKPZOC":[
          "LTM4LjU3MTkwNw==fniChHJyZlxOMTY=",
          "eLTMuODE0MDU2Mg==SlqrZLsZFSsMTY="
        ]
      }
    },
    {
      "type":"Feature",
      "properties":{
        "AGRAVO":"DENGUE"
      },
      "geometry":{
        "type":"Point",
        "coordinates":[
          null,
          null
        ],
        "YZEPBZDRJSEWSDOEWSUWBYEIRJVINSTYQIXVWGRNFIDUJGAYNSIRXXHIZUTRECKPZOC":[
          "LTM4LjU4NjE4NQ==isHAqzqtgVyLMTY=",
          "sLTMuNzY5MDQ1NA==LdsSSNDLKllMTY="
        ]
      }
    },
    {
      "type":"Feature",
      "properties":{
        "AGRAVO":"DENGUE"
      },
      "geometry":{
        "type":"Point",
        "coordinates":[
          null,
          null
        ],
        "YZEPBZDRJSEWSDOEWSUWBYEIRJVINSTYQIXVWGRNFIDUJGAYNSIRXXHIZUTRECKPZOC":[
          "LTM4LjQ0ODc5NQ==FfRyjPlGvIlDMTY=",
          "fLTMuNzk0NTA4Mg==APxLOSziDSYMTY="
        ]
      }
    },
    {
      "type":"Feature",
      "properties":{
        "AGRAVO":"DENGUE"
      },
      "geometry":{
        "type":"Point",
        "coordinates":[
          null,
          null
        ],
        "YZEPBZDRJSEWSDOEWSUWBYEIRJVINSTYQIXVWGRNFIDUJGAYNSIRXXHIZUTRECKPZOC":[
          "LTM4LjU2ODY5NQ==VgftBAffyTDZMTY=",
          "KLTMuNzYwMDM0lvNSlpBMpaeeXfBMTI="
        ]
      }
    },
    {
      "type":"Feature",
      "properties":{
        "AGRAVO":"DENGUE"
      },
      "geometry":{
        "type":"Point",
        "coordinates":[
          null,
          null
        ],
        "YZEPBZDRJSEWSDOEWSUWBYEIRJVINSTYQIXVWGRNFIDUJGAYNSIRXXHIZUTRECKPZOC":[
          "LTM4LjUyODI=UhPnTLRGtkpPeglUMTI=",
          "WLTMuODI2ODg3eCFzFpTzMVIquawMTI="
        ]
      }
    },
    {
      "type":"Feature",
      "properties":{
        "AGRAVO":"DENGUE"
      },
      "geometry":{
        "type":"Point",
        "coordinates":[
          null,
          null
        ],
        "YZEPBZDRJSEWSDOEWSUWBYEIRJVINSTYQIXVWGRNFIDUJGAYNSIRXXHIZUTRECKPZOC":[
          "LTM4LjU4NTQzOA==JfOeDPaXSOEWMTY=",
          "lLTMuNzc3NDkxJapNYixtnvTbFjFMTI="
        ]
      }
    },
    {
      "type":"Feature",
      "properties":{
        "AGRAVO":"DENGUE"
      },
      "geometry":{
        "type":"Point",
        "coordinates":[
          null,
          null
        ],
        "YZEPBZDRJSEWSDOEWSUWBYEIRJVINSTYQIXVWGRNFIDUJGAYNSIRXXHIZUTRECKPZOC":[
          "LTM4LjU2MDI2keyNTQoXyATvlNXsMTI=",
          "BLTMuNzU2MDUzMg==PPXCenpsghUMTY="
        ]
      }
    },
    {
      "type":"Feature",
      "properties":{
        "AGRAVO":"DENGUE"
      },
      "geometry":{
        "type":"Point",
        "coordinates":[
          null,
          null
        ],
        "YZEPBZDRJSEWSDOEWSUWBYEIRJVINSTYQIXVWGRNFIDUJGAYNSIRXXHIZUTRECKPZOC":[
          "LTM4LjU4NzQ2Nw==wzCEnNHRnmjvMTY=",
          "CLTMuNzk1MzczmQLHLjgXMJkMtKwMTI="
        ]
      }
    }
  ]
}