{
  "type":"FeatureCollection",
  "features":[
    {
      "type":"Feature",
      "properties":{
        "AGRAVO":"DENGUE"
      },
      "geometry":{
        "type":"Point",
        "coordinates":[
          null,
          null
        ],
        "MHKZHIMWQNHPARYHWNRPEWBKAVNJJYRAMBQIYGBWVFUAMOXKGXMXPZFDTKJIHSCUFXZULUNQELGYHDHXBWRPCKZAIJMEYNMXS":[
          "VLTMuODMzOTg3Nw==nfgnskqVCenMTY=",
          "LTM4LjU3NTIztAvAddAucknmqwWjMTI="
        ]
      }
    },
    {
      "type":"Feature",
      "properties":{
        "AGRAVO":"DENGUE"
      },
      "geometry":{
        "type":"Point",
        "coordinates":[
          null,
          null
        ],
        "MHKZHIMWQNHPARYHWNRPEWBKAVNJJYRAMBQIYGBWVFUAMOXKGXMXPZFDTKJIHSCUFXZULUNQELGYHDHXBWRPCKZAIJMEYNMXS":[
          "ZLTMuNzIyMjk2Nw==PXizRhfwziLMTY=",
          "LTM4LjU5OTA4ASVtxJTZepdgZCVZMTI="
        ]
      }
    },
    {
      "type":"Feature",
      "properties":{
        "AGRAVO":"DENGUE"
      },
      "geometry":{
        "type":"Point",
        "coordinates":[
          null,
          null
        ],
        "MHKZHIMWQNHPARYHWNRPEWBKAVNJJYRAMBQIYGBWVFUAMOXKGXMXPZFDTKJIHSCUFXZULUNQELGYHDHXBWRPCKZAIJMEYNMXS":[
          "ZLTMuNzI4MjMwNw==DscUzbnITPPMTY=",
          "LTM4LjUxNDE4Mw==xzCwnNjZGwhhMTY="
        ]
      }
    },
    {
      "type":"Feature",
      "properties":{
        "AGRAVO":"DENGUE"
      },
      "geometry":{
        "type":"Point",
        "coordinates":[
          null,
          null
        ],
        "MHKZHIMWQNHPARYHWNRPEWBKAVNJJYRAMBQIYGBWVFUAMOXKGXMXPZFDTKJIHSCUFXZULUNQELGYHDHXBWRPCKZAIJMEYNMXS":[
          "MLTMuODIxOTY2NA==SthVeCXFjZdMTY=",
          "LTM4LjUxMTA3NA==ZUGDVqczRiehMTY="
        ]
      }
    },
    {
      "type":"Feature",
      "properties":{
        "AGRAVO":"DENGUE"
      },
      "geometry":{
        "type":"Point",
        "coordinates":[
          null,
          null
        ],
        "MHKZHIMWQNHPARYHWNRPEWBKAVNJJYRAMBQIYGBWVFUAMOXKGXMXPZFDTKJIHSCUFXZULUNQELGYHDHXBWRPCKZAIJMEYNMXS":[
          "rLTMuNzYzMTIwNA==OcLxfgCQCCUMTY=",
          "LTM4LjUxMzQ3Nw==NwcFxcsPaStZMTY="
        ]
      }
    },
    {
      "type":"Feature",
      "properties":{
        "AGRAVO":"DENGUE"
      },
      "geometry":{
        "type":"Point",
        "coordinates":[
          null,
          null
        ],
        "MHKZHIMWQNHPARYHWNRPEWBKAVNJJYRAMBQIYGBWVFUAMOXKGXMXPZFDTKJIHSCUFXZULUNQELGYHDHXBWRPCKZAIJMEYNMXS":[
          "ZLTMuNzM0Nzc2CpphTmmrzNAnDeBMTI=",
          "LTM4LjU5OTgwOA==JVPwVIkVEZxkMTY="
        ]
      }
    },
    {
      "type":"Feature",
      "properties":{
        "AGRAVO":"DENGUE"
      },
      "geometry":{
        "type":"Point",
        "coordinates":[
          null,
          null
        ],
        "MHKZHIMWQNHPARYHWNRPEWBKAVNJJYRAMBQIYGBWVFUAMOXKGXMXPZFDTKJIHSCUFXZULUNQELGYHDHXBWRPCKZAIJMEYNMXS":[
          "gLTMuODEzNTg5EeKmBOXlTQKYQoyMTI=",
          "LTM4LjQ5ODQwNQ==ADdfWnNNmluXMTY="
        ]
      }
    },
    {
      "type":"Feature",
      "properties":{
        "AGRAVO":"DENGUE"
      },
      "geometry":{
        "type":"Point",
        "coordinates":[
          null,
          null
        ],
        "MHKZHIMWQNHPARYHWNRPEWBKAVNJJYRAMBQIYGBWVFUAMOXKGXMXPZFDTKJIHSCUFXZULUNQELGYHDHXBWRPCKZAIJMEYNMXS":[
          "tLTMuNzM1MzQyxiXRKdHyMPQkXBVMTI=",
          "LTM4LjUzMzYyMw==iiHjXfsQrQylMTY="
        ]
      }
    },
    {
      "type":"Feature",
      "properties":{
        "AGRAVO":"DENGUE"
      },
      "geometry":{
        "type":"Point",
        "coordinates":[
          null,
          null
        ],
        "MHKZHIMWQNHPARYHWNRPEWBKAVNJJYRAMBQIYGBWVFUAMOXKGXMXPZFDTKJIHSCUFXZULUNQELGYHDHXBWRPCKZAIJMEYNMXS":[
          "tLTMuNzE3NDI3YbeJQBUSMkPFapKMTI=",
          "LTM4LjU2ODU5Mg==MDhnRPIIWmwrMTY="
        ]
      }
    },
    {
      "type":"Feature",
      "properties":{
        "AGRAVO":"DENGUE"
      },
      "geometry":{
        "type":"Point",
        "coordinates":[
          null,
          null
        ],
        "MHKZHIMWQNHPARYHWNRPEWBKAVNJJYRAMBQIYGBWVFUAMOXKGXMXPZFDTKJIHSCUFXZULUNQELGYHDHXBWRPCKZAIJMEYNMXS":[
          "KLTMuODA1NQ==WjeUIwwrGNiiHVrMTI=",
          "LTM4LjUzNTU3Mg==oPKagplXUQsfMTY="
        ]
      }
    },
    {
      "type":"Feature",
      "properties":{
        "AGRAVO":"DENGUE"
      },
      "geometry":{
        "type":"Point",
        "coordinates":[
          null,
          null
        ],
        "MHKZHIMWQNHPARYHWNRPEWBKAVNJJYRAMBQIYGBWVFUAMOXKGXMXPZFDTKJIHSCUFXZULUNQELGYHDHXBWRPCKZAIJMEYNMXS":[
          "NLTMuNzk0NjQ1bmMGMMQpHgfupQMMTI=",
          "LTM4LjU4MTI3Ng==CpcLhnasKIrjMTY="
        ]
      }
    },
    {
      "type":"Feature",
      "properties":{
        "AGRAVO":"DENGUE"
      },
      "geometry":{
        "type":"Point",
        "coordinates":[
          null,
          null
        ],
        "MHKZHIMWQNHPARYHWNRPEWBKAVNJJYRAMBQIYGBWVFUAMOXKGXMXPZFDTKJIHSCUFXZULUNQELGYHDHXBWRPCKZAIJMEYNMXS":[
          "bLTMuNzMzMDU0Ng==ukCNcVdjmteMTY=",
          "LTM4LjUxNDI0xmpnLKNirvOcrlFDMTI="
        ]
      }
    },
    {
      "type":"Feature",
      "properties":{
        "AGRAVO":"DENGUE"
      },
      "geometry":{
        "type":"Point",
        "coordinates":[
          null,
          null
        ],
        "MHKZHIMWQNHPARYHWNRPEWBKAVNJJYRAMBQIYGBWVFUAMOXKGXMXPZFDTKJIHSCUFXZULUNQELGYHDHXBWRPCKZAIJMEYNMXS":[
          "TLTMuODQ5MDEyNA==NWLCUYiPuXdMTY=",
          "LTM4LjQ4MjE0Mw==ATjzxRxLHMknMTY="
        ]
      }
    },
    {
      "type":"Feature",
      "properties":{
        "AGRAVO":"DENGUE"
      },
      "geometry":{
        "type":"Point",
        "coordinates":[
          null,
          null
        ],
        "MHKZHIMWQNHPARYHWNRPEWBKAVNJJYRAMBQIYGBWVFUAMOXKGXMXPZFDTKJIHSCUFXZULUNQELGYHDHXBWRPCKZAIJMEYNMXS":[
          "yLTMuNzYxOTIwNw==soxQhEfvIWSMTY=",
          "LTM4LjU5MjQ2hApNEOXeeGhoPgKOMTI="
        ]
      }
    }
  ]
}
