{
  "type":"FeatureCollection",
  "features":[
    {
      "type":"Feature",
      "properties":{
        "AGRAVO":"DENGUE"
      },
      "geometry":{
        "type":"Point",
        "coordinates":[
          null,
          null
        ],
        "SQMRLMNWGMDTDZPSEAXVWNGHSFFOCGWCHWIWNDALZSVLMWFWTOC":[
          "LTM4LjUyOTU=RRhQhrTAQTDIxegqMTI=",
          "uLTMuNzUwNDcyNQ==SzdaMJJZucVMTY="
        ]
      }
    },
    {
      "type":"Feature",
      "properties":{
        "AGRAVO":"DENGUE"
      },
      "geometry":{
        "type":"Point",
        "coordinates":[
          null,
          null
        ],
        "SQMRLMNWGMDTDZPSEAXVWNGHSFFOCGWCHWIWNDALZSVLMWFWTOC":[
          "LTM4LjQ3MTYzOA==uJXYGiIRwVLWMTY=",
          "iLTMuODIxNzUyFkzgXqSYuAMeWEUMTI="
        ]
      }
    },
    {
      "type":"Feature",
      "properties":{
        "AGRAVO":"DENGUE"
      },
      "geometry":{
        "type":"Point",
        "coordinates":[
          null,
          null
        ],
        "SQMRLMNWGMDTDZPSEAXVWNGHSFFOCGWCHWIWNDALZSVLMWFWTOC":[
          "LTM4LjU0ODE2NA==TDlVHIiBYIohMTY=",
          "tLTMuNzk5MDAxNw==BjTLrSElRbvMTY="
        ]
      }
    },
    {
      "type":"Feature",
      "properties":{
        "AGRAVO":"DENGUE"
      },
      "geometry":{
        "type":"Point",
        "coordinates":[
          null,
          null
        ],
        "SQMRLMNWGMDTDZPSEAXVWNGHSFFOCGWCHWIWNDALZSVLMWFWTOC":[
          "LTM4LjU2Mjc5OA==lAnmZIMBFybTMTY=",
          "TLTMuODQxNzE5EVDximYPOMOYkKiMTI="
        ]
      }
    },
    {
      "type":"Feature",
      "properties":{
        "AGRAVO":"DENGUE"
      },
      "geometry":{
        "type":"Point",
        "coordinates":[
          null,
          null
        ],
        "SQMRLMNWGMDTDZPSEAXVWNGHSFFOCGWCHWIWNDALZSVLMWFWTOC":[
          "LTM4LjU1NzUxOA==KznuImdYxdUZMTY=",
          "DLTMuODMxNjU4RsilgBvushclubTMTI="
        ]
      }
    },
    {
      "type":"Feature",
      "properties":{
        "AGRAVO":"DENGUE"
      },
      "geometry":{
        "type":"Point",
        "coordinates":[
          null,
          null
        ],
        "SQMRLMNWGMDTDZPSEAXVWNGHSFFOCGWCHWIWNDALZSVLMWFWTOC":[
          "LTM4LjUxNzE0Nw==XjRDrozSnIrIMTY=",
          "fLTMuODQ1MzE2KepKRJCdorvuHtaMTI="
        ]
      }
    },
    {
      "type":"Feature",
      "properties":{
        "AGRAVO":"DENGUE"
      },
      "geometry":{
        "type":"Point",
        "coordinates":[
          null,
          null
        ],
        "SQMRLMNWGMDTDZPSEAXVWNGHSFFOCGWCHWIWNDALZSVLMWFWTOC":[
          "LTM4LjYwNTMxHkaiNeoTSBkscBnSMTI=",
          "DLTMuNzU5ODM3OQ==XhSKdCEKmhKMTY="
        ]
      }
    },
    {
      "type":"Feature",
      "properties":{
        "AGRAVO":"DENGUE"
      },
      "geometry":{
        "type":"Point",
        "coordinates":[
          null,
          null
        ],
        "SQMRLMNWGMDTDZPSEAXVWNGHSFFOCGWCHWIWNDALZSVLMWFWTOC":[
          "LTM4LjU3NDQ4gJikWIQqxgwogwQQMTI=",
          "NLTMuODMwNTc4Ng==wwgPeshOXfhMTY="
        ]
      }
    },
    {
      "type":"Feature",
      "properties":{
        "AGRAVO":"DENGUE"
      },
      "geometry":{
        "type":"Point",
        "coordinates":[
          null,
          null
        ],
        "SQMRLMNWGMDTDZPSEAXVWNGHSFFOCGWCHWIWNDALZSVLMWFWTOC":[
          "LTM4LjU2Mjc1Ng==wwOmrlaEDoajMTY=",
          "RLTMuODQwOTA2OqVdYckbiErnooYMTI="
        ]
      }
    },
    {
      "type":"Feature",
      "properties":{
        "AGRAVO":"DENGUE"
      },
      "geometry":{
        "type":"Point",
        "coordinates":[
          null,
          null
        ],
        "SQMRLMNWGMDTDZPSEAXVWNGHSFFOCGWCHWIWNDALZSVLMWFWTOC":[
          "LTM4LjU0NDA2Nw==BiPGFGRLoOTfMTY=",
          "wLTMuNzU5NTg2OA==qsqzebZOgcUMTY="
        ]
      }
    },
    {
      "type":"Feature",
      "properties":{
        "AGRAVO":"DENGUE"
      },
      "geometry":{
        "type":"Point",
        "coordinates":[
          null,
          null
        ],
        "SQMRLMNWGMDTDZPSEAXVWNGHSFFOCGWCHWIWNDALZSVLMWFWTOC":[
          "LTM4LjU3NDUxNg==EbcPnFCOWzvbMTY=",
          "zLTMuODMwNjg=buxoFhRAfVEcwTdMTI="
        ]
      }
    },
    {
      "type":"Feature",
      "properties":{
        "AGRAVO":"DENGUE"
      },
      "geometry":{
        "type":"Point",
        "coordinates":[
          null,
          null
        ],
        "SQMRLMNWGMDTDZPSEAXVWNGHSFFOCGWCHWIWNDALZSVLMWFWTOC":[
          "LTM4LjU1MDY2Nw==ortsoGHrKnpDMTY=",
          "XLTMuODEyMzUxNw==mBwVATCBqQeMTY="
        ]
      }
    },
    {
      "type":"Feature",
      "properties":{
        "AGRAVO":"DENGUE"
      },
      "geometry":{
        "type":"Point",
        "coordinates":[
          null,
          null
        ],
        "SQMRLMNWGMDTDZPSEAXVWNGHSFFOCGWCHWIWNDALZSVLMWFWTOC":[
          "LTM4LjQ2NTczNg==YWgaXfZorfcaMTY=",
          "BLTMuODMzMzIxHGkImRYuqyANdVUMTI="
        ]
      }
    },
    {
      "type":"Feature",
      "properties":{
        "AGRAVO":"DENGUE"
      },
      "geometry":{
        "type":"Point",
        "coordinates":[
          null,
          null
        ],
        "SQMRLMNWGMDTDZPSEAXVWNGHSFFOCGWCHWIWNDALZSVLMWFWTOC":[
          "LTM4LjU0MzQyNw==yrlkOxOtueTHMTY=",
          "DLTMuNzY2MTA0wDkFvYYytRLZjUPMTI="
        ]
      }
    },
    {
      "type":"Feature",
      "properties":{
        "AGRAVO":"DENGUE"
      },
      "geometry":{
        "type":"Point",
        "coordinates":[
          null,
          null
        ],
        "SQMRLMNWGMDTDZPSEAXVWNGHSFFOCGWCHWIWNDALZSVLMWFWTOC":[
          "LTM4LjU1MzQ0OAlgZdTVYtQWtRLTMTI=",
          "qLTMuNzc2MDc0sZJMQQRMZTNrFxiMTI="
        ]
      }
    },
    {
      "type":"Feature",
      "properties":{
        "AGRAVO":"DENGUE"
      },
      "geometry":{
        "type":"Point",
        "coordinates":[
          null,
          null
        ],
        "SQMRLMNWGMDTDZPSEAXVWNGHSFFOCGWCHWIWNDALZSVLMWFWTOC":[
          "LTM4LjUxMTI3OXbiqhMzxaEdgSlnMTI=",
          "XLTMuODIwNTM5Mg==TRPwobKxOrnMTY="
        ]
      }
    },
    {
      "type":"Feature",
      "properties":{
        "AGRAVO":"DENGUE"
      },
      "geometry":{
        "type":"Point",
        "coordinates":[
          null,
          null
        ],
        "SQMRLMNWGMDTDZPSEAXVWNGHSFFOCGWCHWIWNDALZSVLMWFWTOC":[
          "LTM4LjU5NjQ3JFToBrQGqFSLEYslMTI=",
          "OLTMuNzY0OTg4rvJJALNxFspgvZTMTI="
        ]
      }
    },
    {
      "type":"Feature",
      "properties":{
        "AGRAVO":"DENGUE"
      },
      "geometry":{
        "type":"Point",
        "coordinates":[
          null,
          null
        ],
        "SQMRLMNWGMDTDZPSEAXVWNGHSFFOCGWCHWIWNDALZSVLMWFWTOC":[
          "LTM4LjUyMzE2qjosXUuMnABqSEkSMTI=",
          "xLTMuODQxNDYwMg==fHDNkFoltofMTY="
        ]
      }
    },
    {
      "type":"Feature",
      "properties":{
        "AGRAVO":"DENGUE"
      },
      "geometry":{
        "type":"Point",
        "coordinates":[
          null,
          null
        ],
        "SQMRLMNWGMDTDZPSEAXVWNGHSFFOCGWCHWIWNDALZSVLMWFWTOC":[
          "LTM4LjUwMzQ4aGToZaRhIdJMzEKAMTI=",
          "aLTMuODc3OTI1AIxrhwcDxNTKcumMTI="
        ]
      }
    },
    {
      "type":"Feature",
      "properties":{
        "AGRAVO":"DENGUE"
      },
      "geometry":{
        "type":"Point",
        "coordinates":[
          null,
          null
        ],
        "SQMRLMNWGMDTDZPSEAXVWNGHSFFOCGWCHWIWNDALZSVLMWFWTOC":[
          "LTM4LjQ3ODU0Ng==aDcGpjLMCwvpMTY=",
          "xLTMuNzkxNzQ2NA==ofwjcUWBOjQMTY="
        ]
      }
    }
  ]
}
